{
    "user": "default",
    "data_settings": {
        "witness_list": [
            "Base",
            "E1",
            "E2",
            "Q",
            "T",
            "Ss"
        ],
        "language": "grc",
        "base_text": "Base",
        "base_text_siglum": "Base"
    },
    "_model": "collation",
    "project": "default",
    "context": "D662S600",
    "structure": {
        "overtext": [
            {
                "id": "Base",
                "tokens": [
                    {
                        "expanded": "e",
                        "rule_match": [
                            "e",
                            "⁊"
                        ],
                        "index": "2",
                        "t": "e",
                        "reading": "Base",
                        "original": "⁊"
                    },
                    {
                        "reading": "Base",
                        "original": "fueronse",
                        "rule_match": [
                            "fueronse"
                        ],
                        "index": "4",
                        "t": "fueronse"
                    },
                    {
                        "reading": "Base",
                        "original": "ferir",
                        "rule_match": [
                            "ferir"
                        ],
                        "index": "6",
                        "t": "ferir"
                    },
                    {
                        "reading": "Base",
                        "original": "uno",
                        "rule_match": [
                            "uno"
                        ],
                        "index": "8",
                        "t": "uno"
                    },
                    {
                        "reading": "Base",
                        "original": "aotro",
                        "rule_match": [
                            "aotro"
                        ],
                        "index": "10",
                        "t": "aotro"
                    },
                    {
                        "expanded": "tan",
                        "rule_match": [
                            "tan",
                            "tā"
                        ],
                        "index": "12",
                        "t": "tan",
                        "reading": "Base",
                        "original": "tā"
                    },
                    {
                        "reading": "Base",
                        "original": "de",
                        "rule_match": [
                            "de"
                        ],
                        "index": "14",
                        "t": "de"
                    },
                    {
                        "reading": "Base",
                        "original": "Rezio",
                        "rule_match": [
                            "Rezio"
                        ],
                        "index": "16",
                        "t": "Rezio"
                    },
                    {
                        "expanded": "quelas",
                        "rule_match": [
                            "quelas",
                            "q̄las"
                        ],
                        "index": "18",
                        "t": "quelas",
                        "reading": "Base",
                        "original": "q̄las"
                    },
                    {
                        "reading": "Base",
                        "original": "lanças",
                        "rule_match": [
                            "lanças"
                        ],
                        "index": "20",
                        "t": "lanças"
                    },
                    {
                        "expanded": "fizieron",
                        "rule_match": [
                            "fizieron",
                            "fizierō"
                        ],
                        "index": "22",
                        "t": "fizieron",
                        "reading": "Base",
                        "original": "fizierō"
                    },
                    {
                        "expanded": "quebrar",
                        "rule_match": [
                            "quebrar",
                            "q̄brar"
                        ],
                        "index": "24",
                        "t": "quebrar",
                        "reading": "Base",
                        "original": "q̄brar"
                    },
                    {
                        "reading": "Base",
                        "original": "por",
                        "rule_match": [
                            "por"
                        ],
                        "index": "26",
                        "t": "por"
                    },
                    {
                        "reading": "Base",
                        "original": "medio.",
                        "rule_match": [
                            "medio."
                        ],
                        "index": "28",
                        "t": "medio."
                    }
                ]
            }
        ],
        "marked_readings": {
            "regularised": [
                {
                    "name": [
                        "Regularised"
                    ],
                    "start": 4,
                    "identifier": [
                        "r"
                    ],
                    "unit_id": "5c52d2039fd3e816f51e0441e24a0a6d",
                    "suffixed_sigla": [
                        true
                    ],
                    "value": "regularised",
                    "reading_text": "fueron se",
                    "witness": "E2",
                    "end": 4,
                    "parent_text": "fueronse",
                    "apparatus": "apparatus",
                    "subreading": [
                        false
                    ],
                    "suffixed_label": [
                        false
                    ]
                }
            ]
        },
        "hand_id_map": {
            "Ss": "Ss",
            "Base": "Base",
            "E1": "E1",
            "E2": "E2",
            "Q": "Q",
            "T": "T"
        },
        "event_list": [
            "combine apparatus unit 1 with unit 2.",
            "make offset reading of type regularised in apparatus unit 1 of reading 1 as a subreading of 22f8cbb43b3a775734afc0ed35754764.",
            "recombine readings in unit 1in  apparatus apparatus.",
            "combine apparatus unit 3 with unit 4.",
            "combine apparatus unit 3 with unit 4.",
            "combine apparatus unit 4 with unit 5.",
            "combine apparatus unit 4 with unit 5.",
            "combine apparatus unit 5 with unit 6.",
            "combine apparatus unit 8 with unit 9.",
            "saved state"
        ],
        "om_readings": [
            "E1",
            "Q",
            "Ss"
        ],
        "lac_readings": [],
        "overtext_name": "Base",
        "apparatus": [
            {
                "first_word_index": "2.1",
                "end": 2,
                "start": 2,
                "readings": [
                    {
                        "label": "a",
                        "suffixes": [
                            "",
                            "r",
                            ""
                        ],
                        "text": [
                            {
                                "Base": {
                                    "original": "⁊",
                                    "t": "e",
                                    "rule_match": [
                                        "e",
                                        "⁊"
                                    ],
                                    "index": "2",
                                    "expanded": "e"
                                },
                                "interface": "e",
                                "index": "2.1",
                                "reading": [
                                    "Base",
                                    "T",
                                    "E2"
                                ],
                                "E2": {
                                    "n": "e",
                                    "original": "Et",
                                    "decision_details": [
                                        {
                                            "n": "e",
                                            "class": "regularised",
                                            "t": "Et",
                                            "scope": "once",
                                            "_id": "verse_D661S600_529d4094-6222-4dc4-890c-446077a3db23"
                                        }
                                    ],
                                    "index": "2",
                                    "t": "Et",
                                    "rule_match": [
                                        "Et"
                                    ],
                                    "decision_class": [
                                        "regularised"
                                    ]
                                },
                                "T": {
                                    "original": "⁊",
                                    "t": "e",
                                    "rule_match": [
                                        "e",
                                        "⁊"
                                    ],
                                    "index": "2",
                                    "expanded": "e"
                                }
                            }
                        ],
                        "witnesses": [
                            "Base",
                            "E2",
                            "T"
                        ],
                        "_id": "c05ca29ca7d5b5a845f88e66c30aefd7"
                    },
                    {
                        "label": "b",
                        "text": [],
                        "type": "om_verse",
                        "suffixes": [
                            "",
                            "",
                            ""
                        ],
                        "details": "om verse",
                        "witnesses": [
                            "E1",
                            "Q",
                            "Ss"
                        ],
                        "_id": "e6c6911413a7e9b45371d80e8b5413b8"
                    }
                ],
                "_id": "9f757bab2e3ecd0362bb6363937ff3f9"
            },
            {
                "first_word_index": "4.1",
                "end": 4,
                "start": 4,
                "readings": [
                    {
                        "label": "a",
                        "text": [
                            {
                                "reading": [
                                    "Base",
                                    "T"
                                ],
                                "Base": {
                                    "original": "fueronse",
                                    "rule_match": [
                                        "fueronse"
                                    ],
                                    "index": "4",
                                    "t": "fueronse"
                                },
                                "interface": "fueronse",
                                "index": "4.1",
                                "T": {
                                    "original": "fueronse",
                                    "rule_match": [
                                        "fueronse"
                                    ],
                                    "index": "4",
                                    "t": "fueronse"
                                }
                            }
                        ],
                        "suffixes": [
                            "",
                            "r",
                            ""
                        ],
                        "standoff_subreadings": [
                            "E2"
                        ],
                        "SR_text": {
                            "E2": {
                                "text": [
                                    {
                                        "reading": [
                                            "E2"
                                        ],
                                        "interface": "fueron",
                                        "index": "4.1",
                                        "E2": {
                                            "original": "fueron",
                                            "interface": "fueron",
                                            "rule_match": [
                                                "fueron"
                                            ],
                                            "index": "4",
                                            "t": "fueron"
                                        }
                                    },
                                    {
                                        "reading": [
                                            "E2"
                                        ],
                                        "interface": "se",
                                        "index": "4.2",
                                        "E2": {
                                            "original": "se",
                                            "interface": "se",
                                            "rule_match": [
                                                "se"
                                            ],
                                            "index": "6",
                                            "t": "se"
                                        }
                                    }
                                ]
                            }
                        },
                        "witnesses": [
                            "Base",
                            "E2",
                            "T"
                        ],
                        "_id": "22f8cbb43b3a775734afc0ed35754764"
                    },
                    {
                        "label": "b",
                        "text": [],
                        "type": "om_verse",
                        "suffixes": [
                            "",
                            "",
                            ""
                        ],
                        "details": "om verse",
                        "witnesses": [
                            "E1",
                            "Q",
                            "Ss"
                        ],
                        "_id": "45ff12587bba3c38d55a13ad75b731b3"
                    }
                ],
                "_id": "5c52d2039fd3e816f51e0441e24a0a6d"
            },
            {
                "first_word_index": "6.1",
                "end": 6,
                "start": 6,
                "readings": [
                    {
                        "label": "a",
                        "suffixes": [
                            "",
                            "",
                            ""
                        ],
                        "text": [
                            {
                                "Base": {
                                    "original": "ferir",
                                    "rule_match": [
                                        "ferir"
                                    ],
                                    "index": "6",
                                    "t": "ferir"
                                },
                                "interface": "ferir",
                                "index": "6.1",
                                "reading": [
                                    "Base",
                                    "T",
                                    "E2"
                                ],
                                "E2": {
                                    "original": "ferir",
                                    "rule_match": [
                                        "ferir"
                                    ],
                                    "index": "8",
                                    "t": "ferir"
                                },
                                "T": {
                                    "original": "ferir",
                                    "rule_match": [
                                        "ferir"
                                    ],
                                    "index": "6",
                                    "t": "ferir"
                                }
                            }
                        ],
                        "witnesses": [
                            "Base",
                            "E2",
                            "T"
                        ],
                        "_id": "fac2ccf042a85c56a94b96cb0de5ef7f"
                    },
                    {
                        "label": "b",
                        "text": [],
                        "type": "om_verse",
                        "suffixes": [
                            "",
                            "",
                            ""
                        ],
                        "details": "om verse",
                        "witnesses": [
                            "E1",
                            "Q",
                            "Ss"
                        ],
                        "_id": "2e0fe6ad0911e296b7c0f92d287381da"
                    }
                ],
                "_id": "09ff7490dfa6ef107ea8017e0ab3641b"
            },
            {
                "first_word_index": "8.1",
                "end": 10,
                "start": 8,
                "readings": [
                    {
                        "label": "a",
                        "suffixes": [
                            "",
                            ""
                        ],
                        "text": [
                            {
                                "reading": [
                                    "Base",
                                    "T"
                                ],
                                "Base": {
                                    "original": "uno",
                                    "rule_match": [
                                        "uno"
                                    ],
                                    "index": "8",
                                    "t": "uno"
                                },
                                "interface": "uno",
                                "index": "8.1",
                                "T": {
                                    "original": "uno",
                                    "rule_match": [
                                        "uno"
                                    ],
                                    "index": "8",
                                    "t": "uno"
                                }
                            },
                            {
                                "reading": [
                                    "Base",
                                    "T"
                                ],
                                "Base": {
                                    "original": "aotro",
                                    "rule_match": [
                                        "aotro"
                                    ],
                                    "index": "10",
                                    "t": "aotro"
                                },
                                "interface": "aotro",
                                "index": "10.1",
                                "T": {
                                    "original": "aotro",
                                    "rule_match": [
                                        "aotro"
                                    ],
                                    "index": "10",
                                    "t": "aotro"
                                }
                            }
                        ],
                        "witnesses": [
                            "Base",
                            "T"
                        ],
                        "_id": "3f1281877c0472948fe0530f8ce0aa60"
                    },
                    {
                        "label": "b",
                        "suffixes": [
                            ""
                        ],
                        "text": [
                            {
                                "reading": [
                                    "E2"
                                ],
                                "interface": "un",
                                "index": "8.1",
                                "E2": {
                                    "original": "un",
                                    "rule_match": [
                                        "un"
                                    ],
                                    "index": "10",
                                    "t": "un"
                                }
                            },
                            {
                                "reading": [
                                    "E2"
                                ],
                                "interface": "por",
                                "index": "8.2",
                                "E2": {
                                    "original": "por",
                                    "rule_match": [
                                        "por"
                                    ],
                                    "index": "12",
                                    "t": "por"
                                }
                            },
                            {
                                "reading": [
                                    "E2"
                                ],
                                "interface": "otro",
                                "index": "10.1",
                                "E2": {
                                    "original": "otro",
                                    "rule_match": [
                                        "otro"
                                    ],
                                    "index": "14",
                                    "t": "otro"
                                }
                            }
                        ],
                        "witnesses": [
                            "E2"
                        ],
                        "_id": "69237c3358bc3ad243d7877d23e3ca09"
                    },
                    {
                        "label": "c",
                        "text": [],
                        "type": "om_verse",
                        "suffixes": [
                            "",
                            "",
                            ""
                        ],
                        "details": "om verse",
                        "witnesses": [
                            "E1",
                            "Q",
                            "Ss"
                        ],
                        "_id": "bb5c65b6787b39434334048cb6e42f61"
                    }
                ],
                "_id": "320f7ffd3048a8c37e600eefc91b9f8a"
            },
            {
                "first_word_index": "12.1",
                "end": 16,
                "start": 12,
                "readings": [
                    {
                        "label": "a",
                        "suffixes": [
                            "",
                            "r",
                            ""
                        ],
                        "text": [
                            {
                                "Base": {
                                    "original": "tā",
                                    "t": "tan",
                                    "rule_match": [
                                        "tan",
                                        "tā"
                                    ],
                                    "index": "12",
                                    "expanded": "tan"
                                },
                                "interface": "tan",
                                "index": "12.1",
                                "reading": [
                                    "Base",
                                    "T",
                                    "E2"
                                ],
                                "E2": {
                                    "original": "tan",
                                    "rule_match": [
                                        "tan"
                                    ],
                                    "index": "16",
                                    "t": "tan"
                                },
                                "T": {
                                    "original": "tā",
                                    "t": "tan",
                                    "rule_match": [
                                        "tan",
                                        "tā"
                                    ],
                                    "index": "12",
                                    "expanded": "tan"
                                }
                            },
                            {
                                "Base": {
                                    "original": "de",
                                    "rule_match": [
                                        "de"
                                    ],
                                    "index": "14",
                                    "t": "de"
                                },
                                "interface": "de",
                                "index": "14.1",
                                "reading": [
                                    "Base",
                                    "T",
                                    "E2"
                                ],
                                "E2": {
                                    "original": "de",
                                    "rule_match": [
                                        "de"
                                    ],
                                    "index": "18",
                                    "t": "de"
                                },
                                "T": {
                                    "original": "de",
                                    "rule_match": [
                                        "de"
                                    ],
                                    "index": "14",
                                    "t": "de"
                                }
                            },
                            {
                                "Base": {
                                    "original": "Rezio",
                                    "rule_match": [
                                        "Rezio"
                                    ],
                                    "index": "16",
                                    "t": "Rezio"
                                },
                                "interface": "Rezio",
                                "index": "16.1",
                                "reading": [
                                    "Base",
                                    "T",
                                    "E2"
                                ],
                                "E2": {
                                    "n": "Rezio",
                                    "original": "rezio",
                                    "decision_details": [
                                        {
                                            "n": "Rezio",
                                            "class": "regularised",
                                            "t": "rezio",
                                            "scope": "once",
                                            "_id": "verse_D661S600_eb3bb9be-7efa-4812-9f28-5a0a78b4c609"
                                        }
                                    ],
                                    "index": "20",
                                    "t": "rezio",
                                    "rule_match": [
                                        "rezio"
                                    ],
                                    "decision_class": [
                                        "regularised"
                                    ]
                                },
                                "T": {
                                    "original": "Rezio",
                                    "rule_match": [
                                        "Rezio"
                                    ],
                                    "index": "16",
                                    "t": "Rezio"
                                }
                            }
                        ],
                        "witnesses": [
                            "Base",
                            "E2",
                            "T"
                        ],
                        "_id": "81910201eb63c05490225dab1940f3b9"
                    },
                    {
                        "label": "b",
                        "text": [],
                        "type": "om_verse",
                        "suffixes": [
                            "",
                            "",
                            ""
                        ],
                        "details": "om verse",
                        "witnesses": [
                            "E1",
                            "Q",
                            "Ss"
                        ],
                        "_id": "374c6c36e567a90ab9f2b66201bb3287"
                    }
                ],
                "_id": "5d555f312b260d97c052451fdbf12ca3"
            },
            {
                "first_word_index": "18.1",
                "end": 20,
                "start": 18,
                "readings": [
                    {
                        "label": "a",
                        "suffixes": [
                            "",
                            ""
                        ],
                        "text": [
                            {
                                "reading": [
                                    "Base",
                                    "T"
                                ],
                                "Base": {
                                    "original": "q̄las",
                                    "t": "quelas",
                                    "rule_match": [
                                        "quelas",
                                        "q̄las"
                                    ],
                                    "index": "18",
                                    "expanded": "quelas"
                                },
                                "interface": "quelas",
                                "index": "18.1",
                                "T": {
                                    "original": "q̄las",
                                    "t": "quelas",
                                    "rule_match": [
                                        "quelas",
                                        "q̄las"
                                    ],
                                    "index": "18",
                                    "expanded": "quelas"
                                }
                            },
                            {
                                "reading": [
                                    "Base",
                                    "T"
                                ],
                                "Base": {
                                    "original": "lanças",
                                    "rule_match": [
                                        "lanças"
                                    ],
                                    "index": "20",
                                    "t": "lanças"
                                },
                                "interface": "lanças",
                                "index": "20.1",
                                "T": {
                                    "original": "lanças",
                                    "rule_match": [
                                        "lanças"
                                    ],
                                    "index": "20",
                                    "t": "lanças"
                                }
                            }
                        ],
                        "witnesses": [
                            "Base",
                            "T"
                        ],
                        "_id": "3d0e4c9643d677718fc4daae683faf68"
                    },
                    {
                        "label": "b",
                        "suffixes": [
                            ""
                        ],
                        "text": [
                            {
                                "reading": [
                                    "E2"
                                ],
                                "interface": "que",
                                "index": "18.1",
                                "E2": {
                                    "original": "que",
                                    "rule_match": [
                                        "que"
                                    ],
                                    "index": "22",
                                    "t": "que"
                                }
                            }
                        ],
                        "witnesses": [
                            "E2"
                        ],
                        "_id": "ed8ab018f26738bca978372bd621a751"
                    },
                    {
                        "label": "c",
                        "text": [],
                        "type": "om_verse",
                        "suffixes": [
                            "",
                            "",
                            ""
                        ],
                        "details": "om verse",
                        "witnesses": [
                            "E1",
                            "Q",
                            "Ss"
                        ],
                        "_id": "af0cfa78a112da02466edbc7b9ca8fc1"
                    }
                ],
                "_id": "b270000e85fa604980b413d51871b574"
            },
            {
                "first_word_index": "22.1",
                "end": 22,
                "start": 22,
                "readings": [
                    {
                        "label": "a",
                        "suffixes": [
                            "",
                            "",
                            ""
                        ],
                        "text": [
                            {
                                "Base": {
                                    "original": "fizierō",
                                    "t": "fizieron",
                                    "rule_match": [
                                        "fizieron",
                                        "fizierō"
                                    ],
                                    "index": "22",
                                    "expanded": "fizieron"
                                },
                                "interface": "fizieron",
                                "index": "22.1",
                                "reading": [
                                    "Base",
                                    "E2",
                                    "T"
                                ],
                                "E2": {
                                    "original": "fizieron",
                                    "rule_match": [
                                        "fizieron"
                                    ],
                                    "index": "24",
                                    "t": "fizieron"
                                },
                                "T": {
                                    "original": "fizierō",
                                    "t": "fizieron",
                                    "rule_match": [
                                        "fizieron",
                                        "fizierō"
                                    ],
                                    "index": "22",
                                    "expanded": "fizieron"
                                }
                            }
                        ],
                        "witnesses": [
                            "Base",
                            "E2",
                            "T"
                        ],
                        "_id": "2aaf5cdd9c41fa2d29dd9c0d2c715c8c"
                    },
                    {
                        "label": "b",
                        "text": [],
                        "type": "om_verse",
                        "suffixes": [
                            "",
                            "",
                            ""
                        ],
                        "details": "om verse",
                        "witnesses": [
                            "E1",
                            "Q",
                            "Ss"
                        ],
                        "_id": "5177bede9486d769b7ae70d237319bbe"
                    }
                ],
                "_id": "40aae016fd466f8a943ae60dd89c0cbd"
            },
            {
                "first_word_index": "24.1",
                "end": 24,
                "start": 24,
                "readings": [
                    {
                        "label": "a",
                        "suffixes": [
                            "",
                            ""
                        ],
                        "text": [
                            {
                                "reading": [
                                    "Base",
                                    "T"
                                ],
                                "Base": {
                                    "original": "q̄brar",
                                    "t": "quebrar",
                                    "rule_match": [
                                        "quebrar",
                                        "q̄brar"
                                    ],
                                    "index": "24",
                                    "expanded": "quebrar"
                                },
                                "interface": "quebrar",
                                "index": "24.1",
                                "T": {
                                    "original": "q̄brar",
                                    "t": "quebrar",
                                    "rule_match": [
                                        "quebrar",
                                        "q̄brar"
                                    ],
                                    "index": "24",
                                    "expanded": "quebrar"
                                }
                            }
                        ],
                        "witnesses": [
                            "Base",
                            "T"
                        ],
                        "_id": "581d579920d0db1e543d9258c2837e9c"
                    },
                    {
                        "label": "b",
                        "suffixes": [
                            ""
                        ],
                        "text": [
                            {
                                "reading": [
                                    "E2"
                                ],
                                "interface": "crebar",
                                "index": "24.1",
                                "E2": {
                                    "original": "crebar",
                                    "rule_match": [
                                        "crebar"
                                    ],
                                    "index": "26",
                                    "t": "crebar"
                                }
                            }
                        ],
                        "witnesses": [
                            "E2"
                        ],
                        "_id": "c871d69d411f3d00ed66c3ef057dcf98"
                    },
                    {
                        "label": "c",
                        "text": [],
                        "type": "om_verse",
                        "suffixes": [
                            "",
                            "",
                            ""
                        ],
                        "details": "om verse",
                        "witnesses": [
                            "E1",
                            "Q",
                            "Ss"
                        ],
                        "_id": "fc61ac8ac20f1aca50166a6e73657c35"
                    }
                ],
                "_id": "a86d07f6eb1a5ad0356ad034b5b5f805"
            },
            {
                "first_word_index": "25.1",
                "end": 25,
                "start": 25,
                "readings": [
                    {
                        "label": "a",
                        "text": [],
                        "type": "om",
                        "suffixes": [
                            "",
                            ""
                        ],
                        "witnesses": [
                            "Base",
                            "T"
                        ],
                        "_id": "8048c832cc04df1bd173e027e50e12da"
                    },
                    {
                        "label": "b",
                        "suffixes": [
                            ""
                        ],
                        "text": [
                            {
                                "reading": [
                                    "E2"
                                ],
                                "interface": "las",
                                "index": "25.1",
                                "E2": {
                                    "original": "las",
                                    "rule_match": [
                                        "las"
                                    ],
                                    "index": "28",
                                    "t": "las"
                                }
                            },
                            {
                                "reading": [
                                    "E2"
                                ],
                                "interface": "lanças",
                                "index": "25.2",
                                "E2": {
                                    "original": "lanças",
                                    "rule_match": [
                                        "lanças"
                                    ],
                                    "index": "30",
                                    "t": "lanças"
                                }
                            }
                        ],
                        "witnesses": [
                            "E2"
                        ],
                        "_id": "c95b4f8f82a0a6f95ddc571c8f994088"
                    },
                    {
                        "label": "c",
                        "text": [],
                        "type": "om_verse",
                        "suffixes": [
                            "",
                            "",
                            ""
                        ],
                        "details": "om verse",
                        "witnesses": [
                            "E1",
                            "Q",
                            "Ss"
                        ],
                        "_id": "9017691c30b234d80d46ae49a566ec79"
                    }
                ],
                "_id": "66cf02df03884c3199460cfc46e1fb90"
            },
            {
                "first_word_index": "26",
                "end": 28,
                "start": 26,
                "readings": [
                    {
                        "label": "a",
                        "suffixes": [
                            "",
                            "",
                            ""
                        ],
                        "text": [
                            {
                                "Base": {
                                    "original": "por",
                                    "rule_match": [
                                        "por"
                                    ],
                                    "index": "26",
                                    "t": "por"
                                },
                                "interface": "por",
                                "index": "26",
                                "reading": [
                                    "Base",
                                    "E2",
                                    "T"
                                ],
                                "E2": {
                                    "original": "por",
                                    "rule_match": [
                                        "por"
                                    ],
                                    "index": "32",
                                    "t": "por"
                                },
                                "T": {
                                    "original": "por",
                                    "rule_match": [
                                        "por"
                                    ],
                                    "index": "26",
                                    "t": "por"
                                }
                            },
                            {
                                "Base": {
                                    "original": "medio.",
                                    "rule_match": [
                                        "medio."
                                    ],
                                    "index": "28",
                                    "t": "medio."
                                },
                                "interface": "medio.",
                                "index": "28",
                                "reading": [
                                    "Base",
                                    "E2",
                                    "T"
                                ],
                                "E2": {
                                    "original": "medio.",
                                    "rule_match": [
                                        "medio."
                                    ],
                                    "index": "34",
                                    "t": "medio."
                                },
                                "T": {
                                    "original": "medio.",
                                    "rule_match": [
                                        "medio."
                                    ],
                                    "index": "28",
                                    "t": "medio."
                                }
                            }
                        ],
                        "witnesses": [
                            "Base",
                            "E2",
                            "T"
                        ],
                        "_id": "6f1f642b67a118fe7dac80967fbecd33"
                    },
                    {
                        "label": "b",
                        "text": [],
                        "type": "om_verse",
                        "suffixes": [
                            "",
                            "",
                            ""
                        ],
                        "details": "om verse",
                        "witnesses": [
                            "E1",
                            "Q",
                            "Ss"
                        ],
                        "_id": "a1174abbbf40bd290ab5221b8d14c127"
                    }
                ],
                "_id": "94e73bc24748d1ab0326f3c85f7fb5ed"
            }
        ]
    },
    "_meta": {
        "_last_modified_by": "default",
        "_last_modified_time": {
            "$date": 1475674159535
        }
    },
    "display_settings": {
        "view_supplied": true,
        "view_unclear": true,
        "expand_abbreviations": true,
        "use_lemma": true,
        "view_capitalisation": true
    },
    "status": "approved",
    "algorithm_settings": {
        "fuzzy_match": true,
        "distance": 2,
        "algorithm": "auto"
    },
    "_id": "project/default/user/default/collation/approved/D661S600.json"
}