{
    "user": "default",
    "data_settings": {
        "witness_list": [
            "Base",
            "E1",
            "E2",
            "Q",
            "T",
            "Ss"
        ],
        "language": "grc",
        "base_text": "Base",
        "base_text_siglum": "Base"
    },
    "_model": "collation",
    "project": "default",
    "context": "D663S600",
    "structure": {
        "overtext": [
            {
                "id": "Base",
                "tokens": [
                    {
                        "reading": "Base",
                        "original": "¶",
                        "rule_match": [
                            "¶"
                        ],
                        "index": "2",
                        "t": "¶"
                    },
                    {
                        "reading": "Base",
                        "original": "Dos",
                        "rule_match": [
                            "Dos"
                        ],
                        "index": "4",
                        "t": "Dos"
                    },
                    {
                        "reading": "Base",
                        "original": "altos",
                        "rule_match": [
                            "altos"
                        ],
                        "index": "6",
                        "t": "altos"
                    },
                    {
                        "expanded": "omnes",
                        "rule_match": [
                            "omnes",
                            "om̄s"
                        ],
                        "index": "8",
                        "t": "omnes",
                        "reading": "Base",
                        "original": "om̄s"
                    },
                    {
                        "expanded": "que",
                        "rule_match": [
                            "que",
                            "q̄"
                        ],
                        "index": "10",
                        "t": "que",
                        "reading": "Base",
                        "original": "q̄"
                    },
                    {
                        "expanded": "auien",
                        "rule_match": [
                            "auien",
                            "auiē"
                        ],
                        "index": "12",
                        "t": "auien",
                        "reading": "Base",
                        "original": "auiē"
                    },
                    {
                        "reading": "Base",
                        "original": "y",
                        "rule_match": [
                            "y"
                        ],
                        "index": "14",
                        "t": "y"
                    },
                    {
                        "reading": "Base",
                        "original": "estonçes",
                        "rule_match": [
                            "estonçes"
                        ],
                        "index": "16",
                        "t": "estonçes"
                    },
                    {
                        "reading": "Base",
                        "original": "enla",
                        "rule_match": [
                            "enla"
                        ],
                        "index": "18",
                        "t": "enla"
                    },
                    {
                        "reading": "Base",
                        "original": "corte",
                        "rule_match": [
                            "corte"
                        ],
                        "index": "20",
                        "t": "corte"
                    },
                    {
                        "expanded": "que",
                        "rule_match": [
                            "que",
                            "q̄"
                        ],
                        "index": "22",
                        "t": "que",
                        "reading": "Base",
                        "original": "q̄"
                    },
                    {
                        "reading": "Base",
                        "original": "auien",
                        "rule_match": [
                            "auien"
                        ],
                        "index": "24",
                        "t": "auien"
                    },
                    {
                        "expanded": "nonbre",
                        "rule_match": [
                            "nonbre",
                            "nōbre"
                        ],
                        "index": "26",
                        "t": "nonbre",
                        "reading": "Base",
                        "original": "nōbre"
                    },
                    {
                        "reading": "Base",
                        "original": "el",
                        "rule_match": [
                            "el"
                        ],
                        "index": "28",
                        "t": "el"
                    },
                    {
                        "reading": "Base",
                        "original": "uno",
                        "rule_match": [
                            "uno"
                        ],
                        "index": "30",
                        "t": "uno"
                    },
                    {
                        "reading": "Base",
                        "original": "oriozgodos",
                        "rule_match": [
                            "oriozgodos"
                        ],
                        "index": "32",
                        "t": "oriozgodos"
                    },
                    {
                        "expanded": "e",
                        "rule_match": [
                            "e",
                            "⁊"
                        ],
                        "index": "34",
                        "t": "e",
                        "reading": "Base",
                        "original": "⁊"
                    },
                    {
                        "reading": "Base",
                        "original": "el",
                        "rule_match": [
                            "el"
                        ],
                        "index": "36",
                        "t": "el"
                    },
                    {
                        "reading": "Base",
                        "original": "otro",
                        "rule_match": [
                            "otro"
                        ],
                        "index": "38",
                        "t": "otro"
                    },
                    {
                        "reading": "Base",
                        "original": "thyobala.",
                        "rule_match": [
                            "thyobala."
                        ],
                        "index": "40",
                        "t": "thyobala."
                    },
                    {
                        "reading": "Base",
                        "original": "los",
                        "rule_match": [
                            "los"
                        ],
                        "index": "42",
                        "t": "los"
                    },
                    {
                        "expanded": "que",
                        "rule_match": [
                            "que",
                            "q̄"
                        ],
                        "index": "44",
                        "t": "que",
                        "reading": "Base",
                        "original": "q̄"
                    },
                    {
                        "reading": "Base",
                        "original": "deximos",
                        "rule_match": [
                            "deximos"
                        ],
                        "index": "46",
                        "t": "deximos"
                    },
                    {
                        "reading": "Base",
                        "original": "ya",
                        "rule_match": [
                            "ya"
                        ],
                        "index": "48",
                        "t": "ya"
                    },
                    {
                        "reading": "Base",
                        "original": "suso",
                        "rule_match": [
                            "suso"
                        ],
                        "index": "50",
                        "t": "suso"
                    },
                    {
                        "reading": "Base",
                        "original": "enla",
                        "rule_match": [
                            "enla"
                        ],
                        "index": "52",
                        "t": "enla"
                    },
                    {
                        "reading": "Base",
                        "original": "estoria",
                        "rule_match": [
                            "estoria"
                        ],
                        "index": "54",
                        "t": "estoria"
                    }
                ]
            }
        ],
        "marked_readings": {
            "regularised": [
                {
                    "name": [
                        "Regularised"
                    ],
                    "start": 18,
                    "identifier": [
                        "r"
                    ],
                    "unit_id": "e60784a5e3ba1d3dc6688d3e6f644151",
                    "suffixed_sigla": [
                        true
                    ],
                    "value": "regularised",
                    "reading_text": "en la",
                    "witness": "E2",
                    "end": 18,
                    "parent_text": "enla",
                    "apparatus": "apparatus",
                    "subreading": [
                        false
                    ],
                    "suffixed_label": [
                        false
                    ]
                },
                {
                    "name": [
                        "Regularised"
                    ],
                    "start": 52,
                    "identifier": [
                        "r"
                    ],
                    "unit_id": "5a8aa5e47918270c46cbeb3818c09e26",
                    "suffixed_sigla": [
                        true
                    ],
                    "value": "regularised",
                    "reading_text": "en la",
                    "witness": "E2",
                    "end": 52,
                    "parent_text": "enla",
                    "apparatus": "apparatus",
                    "subreading": [
                        false
                    ],
                    "suffixed_label": [
                        false
                    ]
                }
            ]
        },
        "hand_id_map": {
            "Ss": "Ss",
            "Base": "Base",
            "E1": "E1",
            "E2": "E2",
            "Q": "Q",
            "T": "T"
        },
        "event_list": [
            "combine apparatus unit 0 with unit 1.",
            "split apparatus unit 0.",
            "combine apparatus unit 2 with unit 3.",
            "combine apparatus unit 2 with unit 3.",
            "combine apparatus unit 2 with unit 3.",
            "combine apparatus unit 4 with unit 5.",
            "combine apparatus unit 5 with unit 6.",
            "make offset reading of type regularised in apparatus unit 5 of reading 1 as a subreading of 5d761a071b1a97ac6c2a55138ca931bb.",
            "recombine readings in unit 5in  apparatus apparatus.",
            "combine apparatus unit 6 with unit 7.",
            "combine apparatus unit 6 with unit 7.",
            "combine apparatus unit 6 with unit 7.",
            "combine apparatus unit 6 with unit 7.",
            "combine apparatus unit 6 with unit 7.",
            "combine apparatus unit 7 with unit 8.",
            "combine apparatus unit 10 with unit 11.",
            "combine apparatus unit 12 with unit 13.",
            "combine apparatus unit 13 with unit 14.",
            "combine apparatus unit 14 with unit 15.",
            "make offset reading of type regularised in apparatus unit 14 of reading 1 as a subreading of d2e4dd5e37b12fe09ed03c20389a2ab2.",
            "recombine readings in unit 14in  apparatus apparatus.",
            "saved state"
        ],
        "om_readings": [
            "E1",
            "Q",
            "Ss"
        ],
        "lac_readings": [],
        "overtext_name": "Base",
        "apparatus": [
            {
                "first_word_index": "2.1",
                "end": 2,
                "start": 2,
                "readings": [
                    {
                        "label": "a",
                        "suffixes": [
                            "",
                            "",
                            ""
                        ],
                        "text": [
                            {
                                "Base": {
                                    "original": "¶",
                                    "rule_match": [
                                        "¶"
                                    ],
                                    "index": "2",
                                    "t": "¶"
                                },
                                "interface": "¶",
                                "index": "2.1",
                                "reading": [
                                    "Base",
                                    "T",
                                    "E2"
                                ],
                                "E2": {
                                    "original": "¶",
                                    "rule_match": [
                                        "¶"
                                    ],
                                    "index": "2",
                                    "t": "¶"
                                },
                                "T": {
                                    "original": "¶",
                                    "rule_match": [
                                        "¶"
                                    ],
                                    "index": "2",
                                    "t": "¶"
                                }
                            }
                        ],
                        "witnesses": [
                            "Base",
                            "E2",
                            "T"
                        ],
                        "_id": "1e41c7ca4229a114a194a3d2daf1e723"
                    },
                    {
                        "label": "b",
                        "text": [],
                        "type": "om_verse",
                        "suffixes": [
                            "",
                            "",
                            ""
                        ],
                        "details": "om verse",
                        "witnesses": [
                            "E1",
                            "Q",
                            "Ss"
                        ],
                        "_id": "e6c6911413a7e9b45371d80e8b5413b8"
                    }
                ],
                "_id": "e4637d959040beb3de4066ee0992b464"
            },
            {
                "first_word_index": "3.1",
                "end": 3,
                "start": 3,
                "readings": [
                    {
                        "label": "a",
                        "text": [],
                        "type": "om",
                        "suffixes": [
                            "",
                            ""
                        ],
                        "witnesses": [
                            "Base",
                            "T"
                        ],
                        "_id": "2f8b46918b9048307c724bb98d3bfb42"
                    },
                    {
                        "label": "b",
                        "suffixes": [
                            ""
                        ],
                        "text": [
                            {
                                "reading": [
                                    "E2"
                                ],
                                "interface": "Et",
                                "index": "3.1",
                                "E2": {
                                    "original": "Et",
                                    "rule_match": [
                                        "Et"
                                    ],
                                    "index": "4",
                                    "t": "Et"
                                }
                            }
                        ],
                        "witnesses": [
                            "E2"
                        ],
                        "_id": "7492496c3ccf7867ce982b828c520e1b"
                    },
                    {
                        "label": "c",
                        "text": [],
                        "type": "om_verse",
                        "suffixes": [
                            "",
                            "",
                            ""
                        ],
                        "details": "om verse",
                        "witnesses": [
                            "E1",
                            "Q",
                            "Ss"
                        ],
                        "_id": "2fa54b3613fc6cd0de0bf791e8fa2949"
                    }
                ],
                "_id": "10d2e08211424757fbe6f03ae9a55d5e"
            },
            {
                "first_word_index": "4.1",
                "end": 10,
                "start": 4,
                "readings": [
                    {
                        "label": "a",
                        "suffixes": [
                            "",
                            "r",
                            ""
                        ],
                        "text": [
                            {
                                "Base": {
                                    "original": "Dos",
                                    "rule_match": [
                                        "Dos"
                                    ],
                                    "index": "4",
                                    "t": "Dos"
                                },
                                "interface": "Dos",
                                "index": "4.1",
                                "reading": [
                                    "Base",
                                    "T",
                                    "E2"
                                ],
                                "E2": {
                                    "n": "Dos",
                                    "original": "dos",
                                    "decision_details": [
                                        {
                                            "n": "Dos",
                                            "class": "regularised",
                                            "t": "dos",
                                            "scope": "once",
                                            "_id": "verse_D662S600_cc9f1da1-e1df-4029-b414-13d7fe6a2d25"
                                        }
                                    ],
                                    "index": "6",
                                    "t": "dos",
                                    "rule_match": [
                                        "dos"
                                    ],
                                    "decision_class": [
                                        "regularised"
                                    ]
                                },
                                "T": {
                                    "original": "Dos",
                                    "rule_match": [
                                        "Dos"
                                    ],
                                    "index": "4",
                                    "t": "Dos"
                                }
                            },
                            {
                                "Base": {
                                    "original": "altos",
                                    "rule_match": [
                                        "altos"
                                    ],
                                    "index": "6",
                                    "t": "altos"
                                },
                                "interface": "altos",
                                "index": "6.1",
                                "reading": [
                                    "Base",
                                    "T",
                                    "E2"
                                ],
                                "E2": {
                                    "original": "altos",
                                    "rule_match": [
                                        "altos"
                                    ],
                                    "index": "8",
                                    "t": "altos"
                                },
                                "T": {
                                    "original": "altos",
                                    "rule_match": [
                                        "altos"
                                    ],
                                    "index": "6",
                                    "t": "altos"
                                }
                            },
                            {
                                "Base": {
                                    "original": "om̄s",
                                    "t": "omnes",
                                    "rule_match": [
                                        "omnes",
                                        "om̄s"
                                    ],
                                    "index": "8",
                                    "expanded": "omnes"
                                },
                                "interface": "omnes",
                                "index": "8.1",
                                "reading": [
                                    "Base",
                                    "T",
                                    "E2"
                                ],
                                "E2": {
                                    "original": "omnes",
                                    "rule_match": [
                                        "omnes"
                                    ],
                                    "index": "10",
                                    "t": "omnes"
                                },
                                "T": {
                                    "original": "om̄s",
                                    "t": "omnes",
                                    "rule_match": [
                                        "omnes",
                                        "om̄s"
                                    ],
                                    "index": "8",
                                    "expanded": "omnes"
                                }
                            },
                            {
                                "Base": {
                                    "original": "q̄",
                                    "t": "que",
                                    "rule_match": [
                                        "que",
                                        "q̄"
                                    ],
                                    "index": "10",
                                    "expanded": "que"
                                },
                                "interface": "que",
                                "index": "10.1",
                                "reading": [
                                    "Base",
                                    "T",
                                    "E2"
                                ],
                                "E2": {
                                    "original": "que",
                                    "rule_match": [
                                        "que"
                                    ],
                                    "index": "12",
                                    "t": "que"
                                },
                                "T": {
                                    "original": "q̄",
                                    "t": "que",
                                    "rule_match": [
                                        "que",
                                        "q̄"
                                    ],
                                    "index": "10",
                                    "expanded": "que"
                                }
                            }
                        ],
                        "witnesses": [
                            "Base",
                            "E2",
                            "T"
                        ],
                        "_id": "5fe5380ded71c11ac04e9585ee815c35"
                    },
                    {
                        "label": "b",
                        "text": [],
                        "type": "om_verse",
                        "suffixes": [
                            "",
                            "",
                            ""
                        ],
                        "details": "om verse",
                        "witnesses": [
                            "E1",
                            "Q",
                            "Ss"
                        ],
                        "_id": "17fd5b4c1ca773c49dad730c4b39e941"
                    }
                ],
                "_id": "a4c064845afef807ca955fd56e620a6e"
            },
            {
                "first_word_index": "12.1",
                "end": 12,
                "start": 12,
                "readings": [
                    {
                        "label": "a",
                        "suffixes": [
                            "",
                            ""
                        ],
                        "text": [
                            {
                                "reading": [
                                    "Base",
                                    "T"
                                ],
                                "Base": {
                                    "original": "auiē",
                                    "t": "auien",
                                    "rule_match": [
                                        "auien",
                                        "auiē"
                                    ],
                                    "index": "12",
                                    "expanded": "auien"
                                },
                                "interface": "auien",
                                "index": "12.1",
                                "T": {
                                    "original": "auiē",
                                    "t": "auien",
                                    "rule_match": [
                                        "auien",
                                        "auiē"
                                    ],
                                    "index": "12",
                                    "expanded": "auien"
                                }
                            }
                        ],
                        "witnesses": [
                            "Base",
                            "T"
                        ],
                        "_id": "6aa994f2ae08b2b4bde78909e6548001"
                    },
                    {
                        "label": "b",
                        "suffixes": [
                            ""
                        ],
                        "text": [
                            {
                                "reading": [
                                    "E2"
                                ],
                                "interface": "auie",
                                "index": "12.1",
                                "E2": {
                                    "original": "auie",
                                    "rule_match": [
                                        "auie"
                                    ],
                                    "index": "14",
                                    "t": "auie"
                                }
                            }
                        ],
                        "witnesses": [
                            "E2"
                        ],
                        "_id": "a08bdc1b3cdbdb02454e234c1204ca07"
                    },
                    {
                        "label": "c",
                        "text": [],
                        "type": "om_verse",
                        "suffixes": [
                            "",
                            "",
                            ""
                        ],
                        "details": "om verse",
                        "witnesses": [
                            "E1",
                            "Q",
                            "Ss"
                        ],
                        "_id": "d60264681c82f26305b8b3bf02f23ee9"
                    }
                ],
                "_id": "7f032e5e78065b6e96b8b48f04e6c4c8"
            },
            {
                "first_word_index": "14.1",
                "end": 16,
                "start": 14,
                "readings": [
                    {
                        "label": "a",
                        "suffixes": [
                            "",
                            "r",
                            ""
                        ],
                        "text": [
                            {
                                "Base": {
                                    "original": "y",
                                    "rule_match": [
                                        "y"
                                    ],
                                    "index": "14",
                                    "t": "y"
                                },
                                "interface": "y",
                                "index": "14.1",
                                "reading": [
                                    "Base",
                                    "T",
                                    "E2"
                                ],
                                "E2": {
                                    "original": "y",
                                    "rule_match": [
                                        "y"
                                    ],
                                    "index": "16",
                                    "t": "y"
                                },
                                "T": {
                                    "original": "y",
                                    "rule_match": [
                                        "y"
                                    ],
                                    "index": "14",
                                    "t": "y"
                                }
                            },
                            {
                                "Base": {
                                    "original": "estonçes",
                                    "rule_match": [
                                        "estonçes"
                                    ],
                                    "index": "16",
                                    "t": "estonçes"
                                },
                                "interface": "estonçes",
                                "index": "16.1",
                                "reading": [
                                    "Base",
                                    "T",
                                    "E2"
                                ],
                                "E2": {
                                    "n": "estonçes",
                                    "original": "estonces",
                                    "decision_details": [
                                        {
                                            "n": "estonçes",
                                            "class": "regularised",
                                            "t": "estonces",
                                            "scope": "once",
                                            "_id": "verse_D662S600_0fed61de-634b-4432-b4dc-c42284f24083"
                                        }
                                    ],
                                    "index": "18",
                                    "t": "estonces",
                                    "rule_match": [
                                        "estonces"
                                    ],
                                    "decision_class": [
                                        "regularised"
                                    ]
                                },
                                "T": {
                                    "original": "estonçes",
                                    "rule_match": [
                                        "estonçes"
                                    ],
                                    "index": "16",
                                    "t": "estonçes"
                                }
                            }
                        ],
                        "witnesses": [
                            "Base",
                            "E2",
                            "T"
                        ],
                        "_id": "19e8e8d3bfb4418cb5b2b8f07ec41872"
                    },
                    {
                        "label": "b",
                        "text": [],
                        "type": "om_verse",
                        "suffixes": [
                            "",
                            "",
                            ""
                        ],
                        "details": "om verse",
                        "witnesses": [
                            "E1",
                            "Q",
                            "Ss"
                        ],
                        "_id": "015691b7cf05b638695aec3418404bae"
                    }
                ],
                "_id": "38efd028131ed9b56d492c1f750cc417"
            },
            {
                "first_word_index": "18.1",
                "end": 18,
                "start": 18,
                "readings": [
                    {
                        "label": "a",
                        "text": [
                            {
                                "reading": [
                                    "Base",
                                    "T"
                                ],
                                "Base": {
                                    "original": "enla",
                                    "rule_match": [
                                        "enla"
                                    ],
                                    "index": "18",
                                    "t": "enla"
                                },
                                "interface": "enla",
                                "index": "18.1",
                                "T": {
                                    "original": "enla",
                                    "rule_match": [
                                        "enla"
                                    ],
                                    "index": "18",
                                    "t": "enla"
                                }
                            }
                        ],
                        "suffixes": [
                            "",
                            "r",
                            ""
                        ],
                        "standoff_subreadings": [
                            "E2"
                        ],
                        "SR_text": {
                            "E2": {
                                "text": [
                                    {
                                        "reading": [
                                            "E2"
                                        ],
                                        "interface": "en",
                                        "index": "18.1",
                                        "E2": {
                                            "original": "en",
                                            "interface": "en",
                                            "rule_match": [
                                                "en"
                                            ],
                                            "index": "20",
                                            "t": "en"
                                        }
                                    },
                                    {
                                        "reading": [
                                            "E2"
                                        ],
                                        "interface": "la",
                                        "index": "18.2",
                                        "E2": {
                                            "original": "la",
                                            "interface": "la",
                                            "rule_match": [
                                                "la"
                                            ],
                                            "index": "22",
                                            "t": "la"
                                        }
                                    }
                                ]
                            }
                        },
                        "witnesses": [
                            "Base",
                            "E2",
                            "T"
                        ],
                        "_id": "5d761a071b1a97ac6c2a55138ca931bb"
                    },
                    {
                        "label": "b",
                        "text": [],
                        "type": "om_verse",
                        "suffixes": [
                            "",
                            "",
                            ""
                        ],
                        "details": "om verse",
                        "witnesses": [
                            "E1",
                            "Q",
                            "Ss"
                        ],
                        "_id": "b0339c06b878ed33e09bf45485453ba0"
                    }
                ],
                "_id": "e60784a5e3ba1d3dc6688d3e6f644151"
            },
            {
                "first_word_index": "20.1",
                "end": 30,
                "start": 20,
                "readings": [
                    {
                        "label": "a",
                        "suffixes": [
                            "",
                            "r",
                            ""
                        ],
                        "text": [
                            {
                                "Base": {
                                    "original": "corte",
                                    "rule_match": [
                                        "corte"
                                    ],
                                    "index": "20",
                                    "t": "corte"
                                },
                                "interface": "corte",
                                "index": "20.1",
                                "reading": [
                                    "Base",
                                    "T",
                                    "E2"
                                ],
                                "E2": {
                                    "original": "corte",
                                    "rule_match": [
                                        "corte"
                                    ],
                                    "index": "24",
                                    "t": "corte"
                                },
                                "T": {
                                    "original": "corte",
                                    "rule_match": [
                                        "corte"
                                    ],
                                    "index": "20",
                                    "t": "corte"
                                }
                            },
                            {
                                "Base": {
                                    "original": "q̄",
                                    "t": "que",
                                    "rule_match": [
                                        "que",
                                        "q̄"
                                    ],
                                    "index": "22",
                                    "expanded": "que"
                                },
                                "interface": "que",
                                "index": "22.1",
                                "reading": [
                                    "Base",
                                    "T",
                                    "E2"
                                ],
                                "E2": {
                                    "original": "que",
                                    "rule_match": [
                                        "que"
                                    ],
                                    "index": "26",
                                    "t": "que"
                                },
                                "T": {
                                    "original": "q̄",
                                    "t": "que",
                                    "rule_match": [
                                        "que",
                                        "q̄"
                                    ],
                                    "index": "22",
                                    "expanded": "que"
                                }
                            },
                            {
                                "Base": {
                                    "original": "auien",
                                    "rule_match": [
                                        "auien"
                                    ],
                                    "index": "24",
                                    "t": "auien"
                                },
                                "interface": "auien",
                                "index": "24.1",
                                "reading": [
                                    "Base",
                                    "T",
                                    "E2"
                                ],
                                "E2": {
                                    "original": "auiē",
                                    "t": "auien",
                                    "rule_match": [
                                        "auien",
                                        "auiē"
                                    ],
                                    "index": "28",
                                    "expanded": "auien"
                                },
                                "T": {
                                    "original": "auien",
                                    "rule_match": [
                                        "auien"
                                    ],
                                    "index": "24",
                                    "t": "auien"
                                }
                            },
                            {
                                "Base": {
                                    "original": "nōbre",
                                    "t": "nonbre",
                                    "rule_match": [
                                        "nonbre",
                                        "nōbre"
                                    ],
                                    "index": "26",
                                    "expanded": "nonbre"
                                },
                                "interface": "nonbre",
                                "index": "26.1",
                                "reading": [
                                    "Base",
                                    "T",
                                    "E2"
                                ],
                                "E2": {
                                    "n": "nonbre",
                                    "original": "nombre",
                                    "decision_details": [
                                        {
                                            "n": "nonbre",
                                            "class": "regularised",
                                            "t": "nombre",
                                            "scope": "once",
                                            "_id": "verse_D662S600_900bdbd2-31de-4b5d-8941-d4630b230443"
                                        }
                                    ],
                                    "index": "30",
                                    "t": "nombre",
                                    "rule_match": [
                                        "nombre"
                                    ],
                                    "decision_class": [
                                        "regularised"
                                    ]
                                },
                                "T": {
                                    "original": "nōbre",
                                    "t": "nonbre",
                                    "rule_match": [
                                        "nonbre",
                                        "nōbre"
                                    ],
                                    "index": "26",
                                    "expanded": "nonbre"
                                }
                            },
                            {
                                "Base": {
                                    "original": "el",
                                    "rule_match": [
                                        "el"
                                    ],
                                    "index": "28",
                                    "t": "el"
                                },
                                "interface": "el",
                                "index": "28.1",
                                "reading": [
                                    "Base",
                                    "T",
                                    "E2"
                                ],
                                "E2": {
                                    "n": "el",
                                    "original": "ell",
                                    "decision_details": [
                                        {
                                            "n": "el",
                                            "class": "regularised",
                                            "t": "ell",
                                            "scope": "once",
                                            "_id": "verse_D662S600_746e93ab-5226-4e25-8ffc-236013e2e8b0"
                                        }
                                    ],
                                    "index": "32",
                                    "t": "ell",
                                    "rule_match": [
                                        "ell"
                                    ],
                                    "decision_class": [
                                        "regularised"
                                    ]
                                },
                                "T": {
                                    "original": "el",
                                    "rule_match": [
                                        "el"
                                    ],
                                    "index": "28",
                                    "t": "el"
                                }
                            },
                            {
                                "Base": {
                                    "original": "uno",
                                    "rule_match": [
                                        "uno"
                                    ],
                                    "index": "30",
                                    "t": "uno"
                                },
                                "interface": "uno",
                                "index": "30.1",
                                "reading": [
                                    "Base",
                                    "T",
                                    "E2"
                                ],
                                "E2": {
                                    "original": "uno",
                                    "rule_match": [
                                        "uno"
                                    ],
                                    "index": "34",
                                    "t": "uno"
                                },
                                "T": {
                                    "original": "uno",
                                    "rule_match": [
                                        "uno"
                                    ],
                                    "index": "30",
                                    "t": "uno"
                                }
                            }
                        ],
                        "witnesses": [
                            "Base",
                            "E2",
                            "T"
                        ],
                        "_id": "6a660dedf3f5c4e99c07462c697b964a"
                    },
                    {
                        "label": "b",
                        "text": [],
                        "type": "om_verse",
                        "suffixes": [
                            "",
                            "",
                            ""
                        ],
                        "details": "om verse",
                        "witnesses": [
                            "E1",
                            "Q",
                            "Ss"
                        ],
                        "_id": "42cead1ca00e95445de2c6ca592cfb1d"
                    }
                ],
                "_id": "f55cc7d708f3dad17c42352029d44622"
            },
            {
                "first_word_index": "32.1",
                "end": 32,
                "start": 32,
                "readings": [
                    {
                        "label": "a",
                        "suffixes": [
                            "",
                            ""
                        ],
                        "text": [
                            {
                                "reading": [
                                    "Base",
                                    "T"
                                ],
                                "Base": {
                                    "original": "oriozgodos",
                                    "rule_match": [
                                        "oriozgodos"
                                    ],
                                    "index": "32",
                                    "t": "oriozgodos"
                                },
                                "interface": "oriozgodos",
                                "index": "32.1",
                                "T": {
                                    "original": "oriozgodos",
                                    "rule_match": [
                                        "oriozgodos"
                                    ],
                                    "index": "32",
                                    "t": "oriozgodos"
                                }
                            }
                        ],
                        "witnesses": [
                            "Base",
                            "T"
                        ],
                        "_id": "a459eb25418fbd158d319b94c0215f37"
                    },
                    {
                        "label": "b",
                        "suffixes": [
                            ""
                        ],
                        "text": [
                            {
                                "reading": [
                                    "E2"
                                ],
                                "interface": "Orios",
                                "index": "32.1",
                                "E2": {
                                    "original": "Orios",
                                    "rule_match": [
                                        "Orios"
                                    ],
                                    "index": "36",
                                    "t": "Orios"
                                }
                            },
                            {
                                "reading": [
                                    "E2"
                                ],
                                "interface": "godos.",
                                "index": "32.2",
                                "E2": {
                                    "original": "godos.",
                                    "rule_match": [
                                        "godos."
                                    ],
                                    "index": "38",
                                    "t": "godos."
                                }
                            }
                        ],
                        "witnesses": [
                            "E2"
                        ],
                        "_id": "c107d22fd1a38ccaf4c741c115d25f16"
                    },
                    {
                        "label": "c",
                        "text": [],
                        "type": "om_verse",
                        "suffixes": [
                            "",
                            "",
                            ""
                        ],
                        "details": "om verse",
                        "witnesses": [
                            "E1",
                            "Q",
                            "Ss"
                        ],
                        "_id": "05ebdcda5d85514a762e5e0c4a1994f6"
                    }
                ],
                "_id": "21020c6384ee56b7b5036255f180d912"
            },
            {
                "first_word_index": "34",
                "end": 38,
                "start": 34,
                "readings": [
                    {
                        "label": "a",
                        "suffixes": [
                            "",
                            "r",
                            ""
                        ],
                        "text": [
                            {
                                "Base": {
                                    "original": "⁊",
                                    "t": "e",
                                    "rule_match": [
                                        "e",
                                        "⁊"
                                    ],
                                    "index": "34",
                                    "expanded": "e"
                                },
                                "interface": "e",
                                "index": "34",
                                "reading": [
                                    "Base",
                                    "T",
                                    "E2"
                                ],
                                "E2": {
                                    "original": "⁊",
                                    "t": "e",
                                    "rule_match": [
                                        "e",
                                        "⁊"
                                    ],
                                    "index": "40",
                                    "expanded": "e"
                                },
                                "T": {
                                    "original": "⁊",
                                    "t": "e",
                                    "rule_match": [
                                        "e",
                                        "⁊"
                                    ],
                                    "index": "34",
                                    "expanded": "e"
                                }
                            },
                            {
                                "Base": {
                                    "original": "el",
                                    "rule_match": [
                                        "el"
                                    ],
                                    "index": "36",
                                    "t": "el"
                                },
                                "interface": "el",
                                "index": "36",
                                "reading": [
                                    "Base",
                                    "T",
                                    "E2"
                                ],
                                "E2": {
                                    "n": "el",
                                    "original": "ell",
                                    "decision_details": [
                                        {
                                            "n": "el",
                                            "class": "regularised",
                                            "t": "ell",
                                            "scope": "once",
                                            "_id": "verse_D662S600_12f6a337-f7a1-4c4a-8aaf-e8c8ddf0e016"
                                        }
                                    ],
                                    "index": "42",
                                    "t": "ell",
                                    "rule_match": [
                                        "ell"
                                    ],
                                    "decision_class": [
                                        "regularised"
                                    ]
                                },
                                "T": {
                                    "original": "el",
                                    "rule_match": [
                                        "el"
                                    ],
                                    "index": "36",
                                    "t": "el"
                                }
                            },
                            {
                                "Base": {
                                    "original": "otro",
                                    "rule_match": [
                                        "otro"
                                    ],
                                    "index": "38",
                                    "t": "otro"
                                },
                                "interface": "otro",
                                "index": "38",
                                "reading": [
                                    "Base",
                                    "T",
                                    "E2"
                                ],
                                "E2": {
                                    "original": "otro",
                                    "rule_match": [
                                        "otro"
                                    ],
                                    "index": "44",
                                    "t": "otro"
                                },
                                "T": {
                                    "original": "otro",
                                    "rule_match": [
                                        "otro"
                                    ],
                                    "index": "38",
                                    "t": "otro"
                                }
                            }
                        ],
                        "witnesses": [
                            "Base",
                            "E2",
                            "T"
                        ],
                        "_id": "8b76b7e365ebc86324bc7456cba27036"
                    },
                    {
                        "label": "b",
                        "text": [],
                        "type": "om_verse",
                        "suffixes": [
                            "",
                            "",
                            ""
                        ],
                        "details": "om verse",
                        "witnesses": [
                            "E1",
                            "Q",
                            "Ss"
                        ],
                        "_id": "71237e56cb3e122be2fa74be9ebdd418"
                    }
                ],
                "_id": "f74f72161345c9281f0bb52417de05cb"
            },
            {
                "first_word_index": "40.1",
                "end": 40,
                "start": 40,
                "readings": [
                    {
                        "label": "a",
                        "suffixes": [
                            "",
                            ""
                        ],
                        "text": [
                            {
                                "reading": [
                                    "Base",
                                    "T"
                                ],
                                "Base": {
                                    "original": "thyobala.",
                                    "rule_match": [
                                        "thyobala."
                                    ],
                                    "index": "40",
                                    "t": "thyobala."
                                },
                                "interface": "thyobala.",
                                "index": "40.1",
                                "T": {
                                    "original": "thyobala.",
                                    "rule_match": [
                                        "thyobala."
                                    ],
                                    "index": "40",
                                    "t": "thyobala."
                                }
                            }
                        ],
                        "witnesses": [
                            "Base",
                            "T"
                        ],
                        "_id": "5b4fb659d577990e48c7a5d525bb2bc4"
                    },
                    {
                        "label": "b",
                        "suffixes": [
                            ""
                        ],
                        "text": [
                            {
                                "reading": [
                                    "E2"
                                ],
                                "interface": "Tiobalt.",
                                "index": "40.1",
                                "E2": {
                                    "original": "Tiobalt.",
                                    "rule_match": [
                                        "Tiobalt."
                                    ],
                                    "index": "46",
                                    "t": "Tiobalt."
                                }
                            }
                        ],
                        "witnesses": [
                            "E2"
                        ],
                        "_id": "8cc14ea41c47c502c1ebdf135af6e056"
                    },
                    {
                        "label": "c",
                        "text": [],
                        "type": "om_verse",
                        "suffixes": [
                            "",
                            "",
                            ""
                        ],
                        "details": "om verse",
                        "witnesses": [
                            "E1",
                            "Q",
                            "Ss"
                        ],
                        "_id": "6be879a30061bb515abd6db5d403068a"
                    }
                ],
                "_id": "85a155c69435d55a6a73de4996542c4c"
            },
            {
                "first_word_index": "42.1",
                "end": 44,
                "start": 42,
                "readings": [
                    {
                        "label": "a",
                        "suffixes": [
                            "",
                            "",
                            ""
                        ],
                        "text": [
                            {
                                "Base": {
                                    "original": "los",
                                    "rule_match": [
                                        "los"
                                    ],
                                    "index": "42",
                                    "t": "los"
                                },
                                "interface": "los",
                                "index": "42.1",
                                "reading": [
                                    "Base",
                                    "T",
                                    "E2"
                                ],
                                "E2": {
                                    "original": "los",
                                    "rule_match": [
                                        "los"
                                    ],
                                    "index": "48",
                                    "t": "los"
                                },
                                "T": {
                                    "original": "los",
                                    "rule_match": [
                                        "los"
                                    ],
                                    "index": "42",
                                    "t": "los"
                                }
                            },
                            {
                                "Base": {
                                    "original": "q̄",
                                    "t": "que",
                                    "rule_match": [
                                        "que",
                                        "q̄"
                                    ],
                                    "index": "44",
                                    "expanded": "que"
                                },
                                "interface": "que",
                                "index": "44.1",
                                "reading": [
                                    "Base",
                                    "T",
                                    "E2"
                                ],
                                "E2": {
                                    "original": "que",
                                    "rule_match": [
                                        "que"
                                    ],
                                    "index": "50",
                                    "t": "que"
                                },
                                "T": {
                                    "original": "q̄",
                                    "t": "que",
                                    "rule_match": [
                                        "que",
                                        "q̄"
                                    ],
                                    "index": "44",
                                    "expanded": "que"
                                }
                            }
                        ],
                        "witnesses": [
                            "Base",
                            "E2",
                            "T"
                        ],
                        "_id": "77ed038e877b236a4b68fa4aa74e07fe"
                    },
                    {
                        "label": "b",
                        "text": [],
                        "type": "om_verse",
                        "suffixes": [
                            "",
                            "",
                            ""
                        ],
                        "details": "om verse",
                        "witnesses": [
                            "E1",
                            "Q",
                            "Ss"
                        ],
                        "_id": "367a3dbfd88a16588346799fc8f9951e"
                    }
                ],
                "_id": "3ad680a6dab1a42cfcffc09d7a070fb1"
            },
            {
                "first_word_index": "46.1",
                "end": 46,
                "start": 46,
                "readings": [
                    {
                        "label": "a",
                        "suffixes": [
                            "",
                            ""
                        ],
                        "text": [
                            {
                                "reading": [
                                    "Base",
                                    "T"
                                ],
                                "Base": {
                                    "original": "deximos",
                                    "rule_match": [
                                        "deximos"
                                    ],
                                    "index": "46",
                                    "t": "deximos"
                                },
                                "interface": "deximos",
                                "index": "46.1",
                                "T": {
                                    "original": "deximos",
                                    "rule_match": [
                                        "deximos"
                                    ],
                                    "index": "46",
                                    "t": "deximos"
                                }
                            }
                        ],
                        "witnesses": [
                            "Base",
                            "T"
                        ],
                        "_id": "c4bda26101bcd3e20713c3977e23fea5"
                    },
                    {
                        "label": "b",
                        "suffixes": [
                            ""
                        ],
                        "text": [
                            {
                                "reading": [
                                    "E2"
                                ],
                                "interface": "dixiemos",
                                "index": "46.1",
                                "E2": {
                                    "original": "dixiemos",
                                    "rule_match": [
                                        "dixiemos"
                                    ],
                                    "index": "52",
                                    "t": "dixiemos"
                                }
                            }
                        ],
                        "witnesses": [
                            "E2"
                        ],
                        "_id": "fe870d61d185d16c63ae86684a6352ef"
                    },
                    {
                        "label": "c",
                        "text": [],
                        "type": "om_verse",
                        "suffixes": [
                            "",
                            "",
                            ""
                        ],
                        "details": "om verse",
                        "witnesses": [
                            "E1",
                            "Q",
                            "Ss"
                        ],
                        "_id": "ff0e2f1518e0dcf77a5a22fe832d20e6"
                    }
                ],
                "_id": "d6aabc7c43885cf8739c55419ec0b2e3"
            },
            {
                "first_word_index": "48.1",
                "end": 50,
                "start": 48,
                "readings": [
                    {
                        "label": "a",
                        "suffixes": [
                            "",
                            "",
                            ""
                        ],
                        "text": [
                            {
                                "Base": {
                                    "original": "ya",
                                    "rule_match": [
                                        "ya"
                                    ],
                                    "index": "48",
                                    "t": "ya"
                                },
                                "interface": "ya",
                                "index": "48.1",
                                "reading": [
                                    "Base",
                                    "T",
                                    "E2"
                                ],
                                "E2": {
                                    "original": "ya",
                                    "rule_match": [
                                        "ya"
                                    ],
                                    "index": "54",
                                    "t": "ya"
                                },
                                "T": {
                                    "original": "ya",
                                    "rule_match": [
                                        "ya"
                                    ],
                                    "index": "48",
                                    "t": "ya"
                                }
                            },
                            {
                                "Base": {
                                    "original": "suso",
                                    "rule_match": [
                                        "suso"
                                    ],
                                    "index": "50",
                                    "t": "suso"
                                },
                                "interface": "suso",
                                "index": "50.1",
                                "reading": [
                                    "Base",
                                    "T",
                                    "E2"
                                ],
                                "E2": {
                                    "original": "suso",
                                    "rule_match": [
                                        "suso"
                                    ],
                                    "index": "56",
                                    "t": "suso"
                                },
                                "T": {
                                    "original": "suso",
                                    "rule_match": [
                                        "suso"
                                    ],
                                    "index": "50",
                                    "t": "suso"
                                }
                            }
                        ],
                        "witnesses": [
                            "Base",
                            "E2",
                            "T"
                        ],
                        "_id": "881ff75f308dbc9b6d28f324f499db21"
                    },
                    {
                        "label": "b",
                        "text": [],
                        "type": "om_verse",
                        "suffixes": [
                            "",
                            "",
                            ""
                        ],
                        "details": "om verse",
                        "witnesses": [
                            "E1",
                            "Q",
                            "Ss"
                        ],
                        "_id": "071552f3b6040e1e2fb329d4f2d23c67"
                    }
                ],
                "_id": "49187f27bd3224b88b48ee6799b7876e"
            },
            {
                "first_word_index": "51.1",
                "end": 51,
                "start": 51,
                "readings": [
                    {
                        "label": "a",
                        "text": [],
                        "type": "om",
                        "suffixes": [
                            "",
                            ""
                        ],
                        "witnesses": [
                            "Base",
                            "T"
                        ],
                        "_id": "4ea22308942f7317dcb4e975cc8534df"
                    },
                    {
                        "label": "b",
                        "suffixes": [
                            ""
                        ],
                        "text": [
                            {
                                "reading": [
                                    "E2"
                                ],
                                "interface": "ante",
                                "index": "51.1",
                                "E2": {
                                    "original": "ante",
                                    "rule_match": [
                                        "ante"
                                    ],
                                    "index": "58",
                                    "t": "ante"
                                }
                            },
                            {
                                "reading": [
                                    "E2"
                                ],
                                "interface": "desto",
                                "index": "51.2",
                                "E2": {
                                    "original": "desto",
                                    "rule_match": [
                                        "desto"
                                    ],
                                    "index": "60",
                                    "t": "desto"
                                }
                            }
                        ],
                        "witnesses": [
                            "E2"
                        ],
                        "_id": "99c8db6718e7fe765e16c03176ffac8f"
                    },
                    {
                        "label": "c",
                        "text": [],
                        "type": "om_verse",
                        "suffixes": [
                            "",
                            "",
                            ""
                        ],
                        "details": "om verse",
                        "witnesses": [
                            "E1",
                            "Q",
                            "Ss"
                        ],
                        "_id": "c7bcb7f6db818659c3dc34e92712c38b"
                    }
                ],
                "_id": "2e5f5f87ad9345de51008ae2d021bf58"
            },
            {
                "first_word_index": "52.1",
                "end": 52,
                "start": 52,
                "readings": [
                    {
                        "label": "a",
                        "text": [
                            {
                                "reading": [
                                    "Base",
                                    "T"
                                ],
                                "Base": {
                                    "original": "enla",
                                    "rule_match": [
                                        "enla"
                                    ],
                                    "index": "52",
                                    "t": "enla"
                                },
                                "interface": "enla",
                                "index": "52.1",
                                "T": {
                                    "original": "enla",
                                    "rule_match": [
                                        "enla"
                                    ],
                                    "index": "52",
                                    "t": "enla"
                                }
                            }
                        ],
                        "suffixes": [
                            "",
                            "r",
                            ""
                        ],
                        "standoff_subreadings": [
                            "E2"
                        ],
                        "SR_text": {
                            "E2": {
                                "text": [
                                    {
                                        "reading": [
                                            "E2"
                                        ],
                                        "interface": "en",
                                        "index": "52.1",
                                        "E2": {
                                            "original": "en",
                                            "interface": "en",
                                            "rule_match": [
                                                "en"
                                            ],
                                            "index": "62",
                                            "t": "en"
                                        }
                                    },
                                    {
                                        "reading": [
                                            "E2"
                                        ],
                                        "interface": "la",
                                        "index": "52.2",
                                        "E2": {
                                            "original": "la",
                                            "interface": "la",
                                            "rule_match": [
                                                "la"
                                            ],
                                            "index": "64",
                                            "t": "la"
                                        }
                                    }
                                ]
                            }
                        },
                        "witnesses": [
                            "Base",
                            "E2",
                            "T"
                        ],
                        "_id": "d2e4dd5e37b12fe09ed03c20389a2ab2"
                    },
                    {
                        "label": "b",
                        "text": [],
                        "type": "om_verse",
                        "suffixes": [
                            "",
                            "",
                            ""
                        ],
                        "details": "om verse",
                        "witnesses": [
                            "E1",
                            "Q",
                            "Ss"
                        ],
                        "_id": "9ecd6ce7e5b74812281eb59b3f1cd548"
                    }
                ],
                "_id": "5a8aa5e47918270c46cbeb3818c09e26"
            },
            {
                "first_word_index": "54.1",
                "end": 54,
                "start": 54,
                "readings": [
                    {
                        "label": "a",
                        "suffixes": [
                            "",
                            "r",
                            ""
                        ],
                        "text": [
                            {
                                "Base": {
                                    "original": "estoria",
                                    "rule_match": [
                                        "estoria"
                                    ],
                                    "index": "54",
                                    "t": "estoria"
                                },
                                "interface": "estoria",
                                "index": "54.1",
                                "reading": [
                                    "Base",
                                    "T",
                                    "E2"
                                ],
                                "E2": {
                                    "n": "estoria",
                                    "original": "estoria.",
                                    "decision_details": [
                                        {
                                            "n": "estoria",
                                            "class": "regularised",
                                            "t": "estoria.",
                                            "scope": "once",
                                            "_id": "verse_D662S600_8b9d293c-c459-4de9-a74d-5565be4dabab"
                                        }
                                    ],
                                    "index": "66",
                                    "t": "estoria.",
                                    "rule_match": [
                                        "estoria."
                                    ],
                                    "decision_class": [
                                        "regularised"
                                    ]
                                },
                                "T": {
                                    "original": "estoria",
                                    "rule_match": [
                                        "estoria"
                                    ],
                                    "index": "54",
                                    "t": "estoria"
                                }
                            }
                        ],
                        "witnesses": [
                            "Base",
                            "E2",
                            "T"
                        ],
                        "_id": "ef827f40de54a761e172cb1b2c4fe0c9"
                    },
                    {
                        "label": "b",
                        "text": [],
                        "type": "om_verse",
                        "suffixes": [
                            "",
                            "",
                            ""
                        ],
                        "details": "om verse",
                        "witnesses": [
                            "E1",
                            "Q",
                            "Ss"
                        ],
                        "_id": "caa697e71b0740f6712ac0089c1d04c1"
                    }
                ],
                "_id": "e0922b3e806126433267cae263eb2034"
            }
        ]
    },
    "_meta": {
        "_last_modified_by": "default",
        "_last_modified_time": {
            "$date": 1475675735138
        }
    },
    "display_settings": {
        "view_supplied": true,
        "view_unclear": true,
        "expand_abbreviations": true,
        "use_lemma": true,
        "view_capitalisation": true
    },
    "status": "approved",
    "algorithm_settings": {
        "fuzzy_match": true,
        "distance": 2,
        "algorithm": "auto"
    },
    "_id": "project/default/user/default/collation/approved/D662S600.json"
}